{
 "result": [
  {
   "scriptId": "0",
   "url": "sqlmath.mjs",
   "functions": [
    {
     "functionName": "",
     "ranges": [
      {
       "count": 1,
       "endOffset": 57524,
       "startOffset": 0
      }
     ],
     "isBlockCoverage": true
    },
    {
     "functionName": "",
     "ranges": [
      {
       "count": 1,
       "endOffset": 5117,
       "startOffset": 4694
      }
     ],
     "isBlockCoverage": true
    },
    {
     "functionName": "__consoleError",
     "ranges": [
      {
       "count": 3,
       "endOffset": 4768,
       "startOffset": 4733
      }
     ],
     "isBlockCoverage": true
    },
    {
     "functionName": "debug",
     "ranges": [
      {
       "count": 1,
       "endOffset": 5009,
       "startOffset": 4774
      }
     ],
     "isBlockCoverage": true
    },
    {
     "functionName": "assertErrorThrownAsync",
     "ranges": [
      {
       "count": 86,
       "endOffset": 5902,
       "startOffset": 5528
      },
      {
       "count": 1,
       "endOffset": 5711,
       "startOffset": 5704
      },
      {
       "count": 85,
       "endOffset": 5761,
       "startOffset": 5711
      },
      {
       "count": 83,
       "endOffset": 5880,
       "startOffset": 5841
      }
     ],
     "isBlockCoverage": true
    },
    {
     "functionName": "assertInt64",
     "ranges": [
      {
       "count": 14016,
       "endOffset": 6318,
       "startOffset": 5904
      },
      {
       "count": 14009,
       "endOffset": 6125,
       "startOffset": 6089
      },
      {
       "count": 14,
       "endOffset": 6316,
       "startOffset": 6133
      }
     ],
     "isBlockCoverage": true
    },
    {
     "functionName": "assertJsonEqual",
     "ranges": [
      {
       "count": 4930,
       "endOffset": 6896,
       "startOffset": 6320
      },
      {
       "count": 3,
       "endOffset": 6894,
       "startOffset": 6607
      },
      {
       "count": 1,
       "endOffset": 6766,
       "startOffset": 6749
      },
      {
       "count": 2,
       "endOffset": 6863,
       "startOffset": 6783
      },
      {
       "count": 1,
       "endOffset": 6842,
       "startOffset": 6809
      },
      {
       "count": 1,
       "endOffset": 6863,
       "startOffset": 6859
      }
     ],
     "isBlockCoverage": true
    },
    {
     "functionName": "assertNumericalEqual",
     "ranges": [
      {
       "count": 4,
       "endOffset": 7336,
       "startOffset": 6898
      },
      {
       "count": 2,
       "endOffset": 7334,
       "startOffset": 7133
      },
      {
       "count": 1,
       "endOffset": 7282,
       "startOffset": 7265
      },
      {
       "count": 1,
       "endOffset": 7303,
       "startOffset": 7299
      }
     ],
     "isBlockCoverage": true
    },
    {
     "functionName": "assertOrThrow",
     "ranges": [
      {
       "count": 49203,
       "endOffset": 7636,
       "startOffset": 7338
      },
      {
       "count": 70,
       "endOffset": 7634,
       "startOffset": 7468
      },
      {
       "count": 14,
       "endOffset": 7595,
       "startOffset": 7552
      },
      {
       "count": 56,
       "endOffset": 7617,
       "startOffset": 7608
      }
     ],
     "isBlockCoverage": true
    },
    {
     "functionName": "childProcessSpawn2",
     "ranges": [
      {
       "count": 15,
       "endOffset": 10182,
       "startOffset": 7638
      }
     ],
     "isBlockCoverage": true
    },
    {
     "functionName": "",
     "ranges": [
      {
       "count": 15,
       "endOffset": 10178,
       "startOffset": 7788
      },
      {
       "count": 1,
       "endOffset": 8126,
       "startOffset": 8000
      },
      {
       "count": 1,
       "endOffset": 8392,
       "startOffset": 8384
      },
      {
       "count": 14,
       "endOffset": 8427,
       "startOffset": 8417
      },
      {
       "count": 1,
       "endOffset": 8541,
       "startOffset": 8533
      },
      {
       "count": 14,
       "endOffset": 8576,
       "startOffset": 8566
      },
      {
       "count": 1,
       "endOffset": 9387,
       "startOffset": 8668
      }
     ],
     "isBlockCoverage": true
    },
    {
     "functionName": "",
     "ranges": [
      {
       "count": 3,
       "endOffset": 9375,
       "startOffset": 8762
      },
      {
       "count": 1,
       "endOffset": 8861,
       "startOffset": 8814
      },
      {
       "count": 2,
       "endOffset": 9374,
       "startOffset": 8861
      }
     ],
     "isBlockCoverage": true
    },
    {
     "functionName": "",
     "ranges": [
      {
       "count": 2,
       "endOffset": 9359,
       "startOffset": 8894
      },
      {
       "count": 1,
       "endOffset": 9169,
       "startOffset": 9070
      },
      {
       "count": 1,
       "endOffset": 9293,
       "startOffset": 9194
      }
     ],
     "isBlockCoverage": true
    },
    {
     "functionName": "",
     "ranges": [
      {
       "count": 15,
       "endOffset": 10170,
       "startOffset": 9413
      }
     ],
     "isBlockCoverage": true
    },
    {
     "functionName": "",
     "ranges": [
      {
       "count": 30,
       "endOffset": 10079,
       "startOffset": 9849
      },
      {
       "count": 2,
       "endOffset": 10005,
       "startOffset": 9963
      },
      {
       "count": 28,
       "endOffset": 10046,
       "startOffset": 10026
      }
     ],
     "isBlockCoverage": true
    },
    {
     "functionName": "ciBuildExt",
     "ranges": [
      {
       "count": 7,
       "endOffset": 11899,
       "startOffset": 10184
      }
     ],
     "isBlockCoverage": true
    },
    {
     "functionName": "ciBuildExt1NodejsConfigure",
     "ranges": [
      {
       "count": 7,
       "endOffset": 15677,
       "startOffset": 11901
      }
     ],
     "isBlockCoverage": true
    },
    {
     "functionName": "",
     "ranges": [
      {
       "count": 14,
       "endOffset": 12706,
       "startOffset": 12347
      },
      {
       "count": 7,
       "endOffset": 12575,
       "startOffset": 12486
      },
      {
       "count": 7,
       "endOffset": 12671,
       "startOffset": 12584
      }
     ],
     "isBlockCoverage": true
    },
    {
     "functionName": "dbCallAsync",
     "ranges": [
      {
       "count": 3912,
       "endOffset": 22672,
       "startOffset": 15679
      },
      {
       "count": 2025,
       "endOffset": 16090,
       "startOffset": 16066
      },
      {
       "count": 1902,
       "endOffset": 18541,
       "startOffset": 16092
      },
      {
       "count": 1887,
       "endOffset": 17603,
       "startOffset": 16482
      },
      {
       "count": 360,
       "endOffset": 17430,
       "startOffset": 17309
      },
      {
       "count": 1887,
       "endOffset": 18525,
       "startOffset": 18118
      },
      {
       "count": 378,
       "endOffset": 18511,
       "startOffset": 18419
      },
      {
       "count": 2010,
       "endOffset": 18839,
       "startOffset": 18541
      },
      {
       "count": 6221,
       "endOffset": 18872,
       "startOffset": 18839
      },
      {
       "count": 2010,
       "endOffset": 20970,
       "startOffset": 18872
      },
      {
       "count": 1985,
       "endOffset": 21138,
       "startOffset": 20970
      },
      {
       "count": 1930,
       "endOffset": 21138,
       "startOffset": 21048
      },
      {
       "count": 2,
       "endOffset": 22104,
       "startOffset": 21138
      },
      {
       "count": 1,
       "endOffset": 22279,
       "startOffset": 22106
      },
      {
       "count": 2,
       "endOffset": 22426,
       "startOffset": 22279
      },
      {
       "count": 55,
       "endOffset": 22670,
       "startOffset": 22426
      }
     ],
     "isBlockCoverage": true
    },
    {
     "functionName": "",
     "ranges": [
      {
       "count": 15942,
       "endOffset": 20478,
       "startOffset": 18936
      },
      {
       "count": 15941,
       "endOffset": 19004,
       "startOffset": 18984
      },
      {
       "count": 216,
       "endOffset": 19038,
       "startOffset": 19006
      },
      {
       "count": 8039,
       "endOffset": 19091,
       "startOffset": 19077
      },
      {
       "count": 9929,
       "endOffset": 19115,
       "startOffset": 19100
      },
      {
       "count": 13984,
       "endOffset": 19769,
       "startOffset": 19124
      },
      {
       "count": 13977,
       "endOffset": 19307,
       "startOffset": 19278
      },
      {
       "count": 12,
       "endOffset": 19355,
       "startOffset": 19329
      },
      {
       "count": 1944,
       "endOffset": 20073,
       "startOffset": 19826
      },
      {
       "count": 2,
       "endOffset": 19952,
       "startOffset": 19947
      },
      {
       "count": 1942,
       "endOffset": 20037,
       "startOffset": 20021
      },
      {
       "count": 14,
       "endOffset": 20144,
       "startOffset": 20083
      },
      {
       "count": 5,
       "endOffset": 20167,
       "startOffset": 20144
      },
      {
       "count": 3,
       "endOffset": 20397,
       "startOffset": 20362
      },
      {
       "count": 11,
       "endOffset": 20477,
       "startOffset": 20397
      }
     ],
     "isBlockCoverage": true
    },
    {
     "functionName": "",
     "ranges": [
      {
       "count": 17883,
       "endOffset": 20644,
       "startOffset": 20544
      },
      {
       "count": 1987,
       "endOffset": 20631,
       "startOffset": 20608
      }
     ],
     "isBlockCoverage": true
    },
    {
     "functionName": "result",
     "ranges": [
      {
       "count": 2,
       "endOffset": 21887,
       "startOffset": 21815
      }
     ],
     "isBlockCoverage": true
    },
    {
     "functionName": "dbCloseAsync",
     "ranges": [
      {
       "count": 3,
       "endOffset": 23254,
       "startOffset": 22674
      },
      {
       "count": 1,
       "endOffset": 23253,
       "startOffset": 23252
      }
     ],
     "isBlockCoverage": true
    },
    {
     "functionName": "",
     "ranges": [
      {
       "count": 1,
       "endOffset": 23249,
       "startOffset": 23020
      }
     ],
     "isBlockCoverage": true
    },
    {
     "functionName": "dbExecAndReturnLastBlob",
     "ranges": [
      {
       "count": 58,
       "endOffset": 23503,
       "startOffset": 23256
      }
     ],
     "isBlockCoverage": true
    },
    {
     "functionName": "dbExecAndReturnLastRow",
     "ranges": [
      {
       "count": 115,
       "endOffset": 23793,
       "startOffset": 23505
      },
      {
       "count": 101,
       "endOffset": 23720,
       "startOffset": 23680
      },
      {
       "count": 1,
       "endOffset": 23725,
       "startOffset": 23720
      },
      {
       "count": 1,
       "endOffset": 23771,
       "startOffset": 23766
      }
     ],
     "isBlockCoverage": true
    },
    {
     "functionName": "dbExecAndReturnLastTable",
     "ranges": [
      {
       "count": 65,
       "endOffset": 24039,
       "startOffset": 23795
      },
      {
       "count": 1,
       "endOffset": 24017,
       "startOffset": 24012
      }
     ],
     "isBlockCoverage": true
    },
    {
     "functionName": "dbExecAndReturnLastValue",
     "ranges": [
      {
       "count": 1184,
       "endOffset": 24251,
       "startOffset": 24041
      }
     ],
     "isBlockCoverage": true
    },
    {
     "functionName": "dbExecAsync",
     "ranges": [
      {
       "count": 1900,
       "endOffset": 26768,
       "startOffset": 24253
      },
      {
       "count": 1,
       "endOffset": 24611,
       "startOffset": 24588
      },
      {
       "count": 1899,
       "endOffset": 24631,
       "startOffset": 24611
      },
      {
       "count": 1235,
       "endOffset": 24962,
       "startOffset": 24631
      },
      {
       "count": 664,
       "endOffset": 25204,
       "startOffset": 24962
      },
      {
       "count": 1887,
       "endOffset": 25483,
       "startOffset": 25204
      },
      {
       "count": 1235,
       "endOffset": 25513,
       "startOffset": 25483
      },
      {
       "count": 652,
       "endOffset": 25547,
       "startOffset": 25530
      },
      {
       "count": 56,
       "endOffset": 25749,
       "startOffset": 25719
      },
      {
       "count": 1831,
       "endOffset": 25864,
       "startOffset": 25766
      },
      {
       "count": 1236,
       "endOffset": 25844,
       "startOffset": 25813
      },
      {
       "count": 595,
       "endOffset": 25864,
       "startOffset": 25861
      },
      {
       "count": 1832,
       "endOffset": 26214,
       "startOffset": 25917
      },
      {
       "count": 1778,
       "endOffset": 26150,
       "startOffset": 26120
      },
      {
       "count": 54,
       "endOffset": 26233,
       "startOffset": 26214
      },
      {
       "count": 110,
       "endOffset": 26269,
       "startOffset": 26238
      },
      {
       "count": 1236,
       "endOffset": 26291,
       "startOffset": 26274
      },
      {
       "count": 1403,
       "endOffset": 26370,
       "startOffset": 26296
      },
      {
       "count": 319,
       "endOffset": 26741,
       "startOffset": 26375
      },
      {
       "count": 1832,
       "endOffset": 26767,
       "startOffset": 26747
      }
     ],
     "isBlockCoverage": true
    },
    {
     "functionName": "",
     "ranges": [
      {
       "count": 1347,
       "endOffset": 24954,
       "startOffset": 24674
      }
     ],
     "isBlockCoverage": true
    },
    {
     "functionName": "",
     "ranges": [
      {
       "count": 516,
       "endOffset": 25196,
       "startOffset": 24995
      }
     ],
     "isBlockCoverage": true
    },
    {
     "functionName": "",
     "ranges": [
      {
       "count": 345,
       "endOffset": 26739,
       "startOffset": 26434
      }
     ],
     "isBlockCoverage": true
    },
    {
     "functionName": "",
     "ranges": [
      {
       "count": 13913,
       "endOffset": 26727,
       "startOffset": 26523
      }
     ],
     "isBlockCoverage": true
    },
    {
     "functionName": "",
     "ranges": [
      {
       "count": 43338,
       "endOffset": 26682,
       "startOffset": 26603
      }
     ],
     "isBlockCoverage": true
    },
    {
     "functionName": "dbExecProfile",
     "ranges": [
      {
       "count": 2,
       "endOffset": 27941,
       "startOffset": 26770
      },
      {
       "count": 1,
       "endOffset": 26973,
       "startOffset": 26949
      },
      {
       "count": 1,
       "endOffset": 27940,
       "startOffset": 26975
      }
     ],
     "isBlockCoverage": true
    },
    {
     "functionName": "",
     "ranges": [
      {
       "count": 1,
       "endOffset": 27227,
       "startOffset": 27095
      }
     ],
     "isBlockCoverage": true
    },
    {
     "functionName": "",
     "ranges": [
      {
       "count": 1491,
       "endOffset": 27420,
       "startOffset": 27318
      },
      {
       "count": 465,
       "endOffset": 27412,
       "startOffset": 27388
      }
     ],
     "isBlockCoverage": true
    },
    {
     "functionName": "",
     "ranges": [
      {
       "count": 20,
       "endOffset": 27801,
       "startOffset": 27463
      }
     ],
     "isBlockCoverage": true
    },
    {
     "functionName": "dbFileLoadAsync",
     "ranges": [
      {
       "count": 17,
       "endOffset": 29444,
       "startOffset": 27943
      },
      {
       "count": 1,
       "endOffset": 28672,
       "startOffset": 28649
      },
      {
       "count": 16,
       "endOffset": 28693,
       "startOffset": 28672
      },
      {
       "count": 1,
       "endOffset": 28735,
       "startOffset": 28693
      },
      {
       "count": 16,
       "endOffset": 28792,
       "startOffset": 28735
      },
      {
       "count": 15,
       "endOffset": 28803,
       "startOffset": 28792
      },
      {
       "count": 15,
       "endOffset": 28978,
       "startOffset": 28967
      },
      {
       "count": 13,
       "endOffset": 29374,
       "startOffset": 28980
      },
      {
       "count": 2,
       "endOffset": 29416,
       "startOffset": 29374
      },
      {
       "count": 15,
       "endOffset": 29443,
       "startOffset": 29416
      }
     ],
     "isBlockCoverage": true
    },
    {
     "functionName": "_dbFileLoad",
     "ranges": [
      {
       "count": 15,
       "endOffset": 28630,
       "startOffset": 28118
      }
     ],
     "isBlockCoverage": true
    },
    {
     "functionName": "dbFileSaveAsync",
     "ranges": [
      {
       "count": 14,
       "endOffset": 29708,
       "startOffset": 29446
      }
     ],
     "isBlockCoverage": true
    },
    {
     "functionName": "dbNoopAsync",
     "ranges": [
      {
       "count": 56,
       "endOffset": 29899,
       "startOffset": 29710
      }
     ],
     "isBlockCoverage": true
    },
    {
     "functionName": "dbOpenAsync",
     "ranges": [
      {
       "count": 32,
       "endOffset": 32503,
       "startOffset": 29901
      },
      {
       "count": 1,
       "endOffset": 30577,
       "startOffset": 30550
      },
      {
       "count": 1,
       "endOffset": 32486,
       "startOffset": 31635
      }
     ],
     "isBlockCoverage": true
    },
    {
     "functionName": "",
     "ranges": [
      {
       "count": 32,
       "endOffset": 31564,
       "startOffset": 30705
      }
     ],
     "isBlockCoverage": true
    },
    {
     "functionName": "",
     "ranges": [
      {
       "count": 1,
       "endOffset": 32465,
       "startOffset": 31913
      }
     ],
     "isBlockCoverage": true
    },
    {
     "functionName": "",
     "ranges": [
      {
       "count": 1,
       "endOffset": 32437,
       "startOffset": 32173
      }
     ],
     "isBlockCoverage": true
    },
    {
     "functionName": "dbTableImportAsync",
     "ranges": [
      {
       "count": 47,
       "endOffset": 35774,
       "startOffset": 32505
      },
      {
       "count": 42,
       "endOffset": 32857,
       "startOffset": 32779
      },
      {
       "count": 2,
       "endOffset": 32985,
       "startOffset": 32882
      },
      {
       "count": 43,
       "endOffset": 33156,
       "startOffset": 32990
      },
      {
       "count": 2,
       "endOffset": 33229,
       "startOffset": 33181
      },
      {
       "count": 1,
       "endOffset": 33316,
       "startOffset": 33287
      },
      {
       "count": 1,
       "endOffset": 33575,
       "startOffset": 33383
      },
      {
       "count": 42,
       "endOffset": 33671,
       "startOffset": 33619
      },
      {
       "count": 42,
       "endOffset": 33803,
       "startOffset": 33673
      },
      {
       "count": 1,
       "endOffset": 33937,
       "startOffset": 33871
      },
      {
       "count": 1,
       "endOffset": 34363,
       "startOffset": 33974
      },
      {
       "count": 1,
       "endOffset": 34594,
       "startOffset": 34456
      },
      {
       "count": 3,
       "endOffset": 35475,
       "startOffset": 35422
      },
      {
       "count": 44,
       "endOffset": 35754,
       "startOffset": 35488
      }
     ],
     "isBlockCoverage": true
    },
    {
     "functionName": "",
     "ranges": [
      {
       "count": 99001,
       "endOffset": 33139,
       "startOffset": 33068
      }
     ],
     "isBlockCoverage": true
    },
    {
     "functionName": "",
     "ranges": [
      {
       "count": 2,
       "endOffset": 33567,
       "startOffset": 33455
      }
     ],
     "isBlockCoverage": true
    },
    {
     "functionName": "",
     "ranges": [
      {
       "count": 714,
       "endOffset": 33794,
       "startOffset": 33726
      }
     ],
     "isBlockCoverage": true
    },
    {
     "functionName": "",
     "ranges": [
      {
       "count": 2,
       "endOffset": 34134,
       "startOffset": 34055
      }
     ],
     "isBlockCoverage": true
    },
    {
     "functionName": "",
     "ranges": [
      {
       "count": 2,
       "endOffset": 34321,
       "startOffset": 34198
      }
     ],
     "isBlockCoverage": true
    },
    {
     "functionName": "",
     "ranges": [
      {
       "count": 4,
       "endOffset": 34309,
       "startOffset": 34246
      }
     ],
     "isBlockCoverage": true
    },
    {
     "functionName": "",
     "ranges": [
      {
       "count": 2,
       "endOffset": 34586,
       "startOffset": 34516
      }
     ],
     "isBlockCoverage": true
    },
    {
     "functionName": "",
     "ranges": [
      {
       "count": 723,
       "endOffset": 35212,
       "startOffset": 34667
      },
      {
       "count": 724,
       "endOffset": 35206,
       "startOffset": 34905
      },
      {
       "count": 723,
       "endOffset": 35017,
       "startOffset": 35008
      },
      {
       "count": 1,
       "endOffset": 35061,
       "startOffset": 35034
      },
      {
       "count": 723,
       "endOffset": 35196,
       "startOffset": 35113
      }
     ],
     "isBlockCoverage": true
    },
    {
     "functionName": "",
     "ranges": [
      {
       "count": 719,
       "endOffset": 35682,
       "startOffset": 35577
      }
     ],
     "isBlockCoverage": true
    },
    {
     "functionName": "fsCopyFileUnlessTest",
     "ranges": [
      {
       "count": 2,
       "endOffset": 36054,
       "startOffset": 35776
      },
      {
       "count": 1,
       "endOffset": 36053,
       "startOffset": 35967
      }
     ],
     "isBlockCoverage": true
    },
    {
     "functionName": "fsExistsUnlessTest",
     "ranges": [
      {
       "count": 10,
       "endOffset": 36394,
       "startOffset": 36056
      },
      {
       "count": 8,
       "endOffset": 36264,
       "startOffset": 36235
      },
      {
       "count": 2,
       "endOffset": 36320,
       "startOffset": 36264
      },
      {
       "count": 1,
       "endOffset": 36392,
       "startOffset": 36320
      }
     ],
     "isBlockCoverage": true
    },
    {
     "functionName": "fsReadFileUnlessTest",
     "ranges": [
      {
       "count": 22,
       "endOffset": 36741,
       "startOffset": 36396
      },
      {
       "count": 8,
       "endOffset": 36627,
       "startOffset": 36592
      },
      {
       "count": 14,
       "endOffset": 36732,
       "startOffset": 36627
      }
     ],
     "isBlockCoverage": true
    },
    {
     "functionName": "fsWriteFileUnlessTest",
     "ranges": [
      {
       "count": 10,
       "endOffset": 37008,
       "startOffset": 36743
      },
      {
       "count": 9,
       "endOffset": 36955,
       "startOffset": 36932
      },
      {
       "count": 1,
       "endOffset": 37007,
       "startOffset": 36955
      }
     ],
     "isBlockCoverage": true
    },
    {
     "functionName": "isExternalBuffer",
     "ranges": [
      {
       "count": 31,
       "endOffset": 37150,
       "startOffset": 37010
      },
      {
       "count": 17,
       "endOffset": 37147,
       "startOffset": 37113
      }
     ],
     "isBlockCoverage": true
    },
    {
     "functionName": "jsbatonCreate",
     "ranges": [
      {
       "count": 2023,
       "endOffset": 37595,
       "startOffset": 37152
      }
     ],
     "isBlockCoverage": true
    },
    {
     "functionName": "jsbatonGetInt64",
     "ranges": [
      {
       "count": 24,
       "endOffset": 37773,
       "startOffset": 37597
      }
     ],
     "isBlockCoverage": true
    },
    {
     "functionName": "jsbatonGetString",
     "ranges": [
      {
       "count": 9,
       "endOffset": 38172,
       "startOffset": 37775
      }
     ],
     "isBlockCoverage": true
    },
    {
     "functionName": "jsbatonSetValue",
     "ranges": [
      {
       "count": 5154,
       "endOffset": 44378,
       "startOffset": 38174
      },
      {
       "count": 5130,
       "endOffset": 39214,
       "startOffset": 39201
      },
      {
       "count": 30,
       "endOffset": 39243,
       "startOffset": 39216
      },
      {
       "count": 4773,
       "endOffset": 39297,
       "startOffset": 39277
      },
      {
       "count": 381,
       "endOffset": 39326,
       "startOffset": 39306
      },
      {
       "count": 24,
       "endOffset": 39375,
       "startOffset": 39359
      },
      {
       "count": 30,
       "endOffset": 39418,
       "startOffset": 39401
      },
      {
       "count": 250,
       "endOffset": 39663,
       "startOffset": 39443
      },
      {
       "count": 12,
       "endOffset": 39586,
       "startOffset": 39491
      },
      {
       "count": 238,
       "endOffset": 39663,
       "startOffset": 39586
      },
      {
       "count": 98,
       "endOffset": 39752,
       "startOffset": 39736
      },
      {
       "count": 98,
       "endOffset": 39793,
       "startOffset": 39777
      },
      {
       "count": 105,
       "endOffset": 39840,
       "startOffset": 39821
      },
      {
       "count": 119,
       "endOffset": 39885,
       "startOffset": 39867
      },
      {
       "count": 125,
       "endOffset": 40048,
       "startOffset": 39910
      },
      {
       "count": 26,
       "endOffset": 40163,
       "startOffset": 40073
      },
      {
       "count": 42,
       "endOffset": 40279,
       "startOffset": 40188
      },
      {
       "count": 36,
       "endOffset": 40399,
       "startOffset": 40305
      },
      {
       "count": 561,
       "endOffset": 40513,
       "startOffset": 40424
      },
      {
       "count": 4032,
       "endOffset": 40688,
       "startOffset": 40538
      },
      {
       "count": 82,
       "endOffset": 41627,
       "startOffset": 40713
      },
      {
       "count": 12,
       "endOffset": 41048,
       "startOffset": 40799
      },
      {
       "count": 70,
       "endOffset": 41110,
       "startOffset": 41048
      },
      {
       "count": 42,
       "endOffset": 41372,
       "startOffset": 41110
      },
      {
       "count": 12,
       "endOffset": 41261,
       "startOffset": 41150
      },
      {
       "count": 30,
       "endOffset": 41372,
       "startOffset": 41261
      },
      {
       "count": 28,
       "endOffset": 41494,
       "startOffset": 41372
      },
      {
       "count": 6,
       "endOffset": 41508,
       "startOffset": 41494
      },
      {
       "count": 22,
       "endOffset": 41542,
       "startOffset": 41521
      },
      {
       "count": 2136,
       "endOffset": 42298,
       "startOffset": 41891
      },
      {
       "count": 30,
       "endOffset": 42504,
       "startOffset": 42478
      },
      {
       "count": 4090,
       "endOffset": 43270,
       "startOffset": 42509
      },
      {
       "count": 1944,
       "endOffset": 42698,
       "startOffset": 42614
      },
      {
       "count": 12,
       "endOffset": 44056,
       "startOffset": 43275
      },
      {
       "count": 561,
       "endOffset": 44188,
       "startOffset": 44061
      },
      {
       "count": 42,
       "endOffset": 44352,
       "startOffset": 44193
      },
      {
       "count": 5142,
       "endOffset": 44377,
       "startOffset": 44358
      }
     ],
     "isBlockCoverage": true
    },
    {
     "functionName": "jsonParseArraybuffer",
     "ranges": [
      {
       "count": 1723,
       "endOffset": 44625,
       "startOffset": 44380
      },
      {
       "count": 1,
       "endOffset": 44570,
       "startOffset": 44539
      },
      {
       "count": 1722,
       "endOffset": 44588,
       "startOffset": 44583
      },
      {
       "count": 1,
       "endOffset": 44616,
       "startOffset": 44607
      }
     ],
     "isBlockCoverage": true
    },
    {
     "functionName": "jsonRowListFromCsv",
     "ranges": [
      {
       "count": 2,
       "endOffset": 49911,
       "startOffset": 44627
      },
      {
       "count": 28,
       "endOffset": 49730,
       "startOffset": 47419
      },
      {
       "count": 2,
       "endOffset": 47864,
       "startOffset": 47472
      },
      {
       "count": 26,
       "endOffset": 47942,
       "startOffset": 47864
      },
      {
       "count": 12,
       "endOffset": 48311,
       "startOffset": 47942
      },
      {
       "count": 14,
       "endOffset": 49724,
       "startOffset": 48311
      },
      {
       "count": 2,
       "endOffset": 48877,
       "startOffset": 48328
      },
      {
       "count": 1,
       "endOffset": 48867,
       "startOffset": 48578
      },
      {
       "count": 12,
       "endOffset": 49724,
       "startOffset": 48877
      },
      {
       "count": 7,
       "endOffset": 49351,
       "startOffset": 48905
      },
      {
       "count": 5,
       "endOffset": 49724,
       "startOffset": 49351
      }
     ],
     "isBlockCoverage": true
    },
    {
     "functionName": "libPlatformArchExt",
     "ranges": [
      {
       "count": 1,
       "endOffset": 50244,
       "startOffset": 49913
      }
     ],
     "isBlockCoverage": true
    },
    {
     "functionName": "listOrEmptyList",
     "ranges": [
      {
       "count": 1,
       "endOffset": 50365,
       "startOffset": 50246
      }
     ],
     "isBlockCoverage": true
    },
    {
     "functionName": "moduleFsInit",
     "ranges": [
      {
       "count": 8,
       "endOffset": 51567,
       "startOffset": 50367
      },
      {
       "count": 6,
       "endOffset": 50587,
       "startOffset": 50564
      },
      {
       "count": 2,
       "endOffset": 50684,
       "startOffset": 50587
      },
      {
       "count": 1,
       "endOffset": 51566,
       "startOffset": 50684
      }
     ],
     "isBlockCoverage": true
    },
    {
     "functionName": "moduleFsInitResolveList",
     "ranges": [
      {
       "count": 1,
       "endOffset": 50794,
       "startOffset": 50713
      }
     ],
     "isBlockCoverage": true
    },
    {
     "functionName": "noop",
     "ranges": [
      {
       "count": 263,
       "endOffset": 51663,
       "startOffset": 51569
      }
     ],
     "isBlockCoverage": true
    },
    {
     "functionName": "objectDeepCopyWithKeysSorted",
     "ranges": [
      {
       "count": 42774,
       "endOffset": 52237,
       "startOffset": 51665
      },
      {
       "count": 16965,
       "endOffset": 51835,
       "startOffset": 51828
      },
      {
       "count": 28326,
       "endOffset": 51864,
       "startOffset": 51837
      },
      {
       "count": 14448,
       "endOffset": 51949,
       "startOffset": 51864
      },
      {
       "count": 2202,
       "endOffset": 52010,
       "startOffset": 51949
      },
      {
       "count": 12246,
       "endOffset": 52236,
       "startOffset": 52010
      }
     ],
     "isBlockCoverage": true
    },
    {
     "functionName": "",
     "ranges": [
      {
       "count": 13714,
       "endOffset": 52214,
       "startOffset": 52130
      }
     ],
     "isBlockCoverage": true
    },
    {
     "functionName": "sqlmathInit",
     "ranges": [
      {
       "count": 3,
       "endOffset": 54372,
       "startOffset": 52239
      },
      {
       "count": 1,
       "endOffset": 52784,
       "startOffset": 52398
      },
      {
       "count": 1,
       "endOffset": 52962,
       "startOffset": 52939
      },
      {
       "count": 2,
       "endOffset": 54370,
       "startOffset": 52962
      },
      {
       "count": 1,
       "endOffset": 53613,
       "startOffset": 53495
      }
     ],
     "isBlockCoverage": true
    },
    {
     "functionName": "dbFinalizationRegistry",
     "ranges": [
      {
       "count": 18,
       "endOffset": 52783,
       "startOffset": 52426
      },
      {
       "count": 1,
       "endOffset": 52777,
       "startOffset": 52733
      }
     ],
     "isBlockCoverage": true
    },
    {
     "functionName": "moduleChildProcessSpawn",
     "ranges": [
      {
       "count": 15,
       "endOffset": 54363,
       "startOffset": 53774
      }
     ],
     "isBlockCoverage": true
    },
    {
     "functionName": "on",
     "ranges": [
      {
       "count": 17,
       "endOffset": 54147,
       "startOffset": 53861
      },
      {
       "count": 2,
       "endOffset": 54042,
       "startOffset": 53948
      },
      {
       "count": 15,
       "endOffset": 54107,
       "startOffset": 54063
      }
     ],
     "isBlockCoverage": true
    },
    {
     "functionName": "sqlmathWebworkerInit",
     "ranges": [
      {
       "count": 1,
       "endOffset": 55452,
       "startOffset": 54374
      }
     ],
     "isBlockCoverage": true
    },
    {
     "functionName": "Worker",
     "ranges": [
      {
       "count": 1,
       "endOffset": 54648,
       "startOffset": 54605
      }
     ],
     "isBlockCoverage": true
    },
    {
     "functionName": "sqlWorker.onmessage",
     "ranges": [
      {
       "count": 2,
       "endOffset": 54807,
       "startOffset": 54729
      }
     ],
     "isBlockCoverage": true
    },
    {
     "functionName": "sqlWorker.postMessage",
     "ranges": [
      {
       "count": 2,
       "endOffset": 54986,
       "startOffset": 54861
      }
     ],
     "isBlockCoverage": true
    },
    {
     "functionName": "",
     "ranges": [
      {
       "count": 2,
       "endOffset": 54974,
       "startOffset": 54902
      }
     ],
     "isBlockCoverage": true
    },
    {
     "functionName": "waitAsync",
     "ranges": [
      {
       "count": 1,
       "endOffset": 55737,
       "startOffset": 55454
      }
     ],
     "isBlockCoverage": true
    },
    {
     "functionName": "",
     "ranges": [
      {
       "count": 1,
       "endOffset": 55733,
       "startOffset": 55550
      }
     ],
     "isBlockCoverage": true
    }
   ]
  },
  {
   "scriptId": "1",
   "url": "test.mjs",
   "functions": [
    {
     "functionName": "",
     "ranges": [
      {
       "count": 1,
       "endOffset": 147386,
       "startOffset": 0
      }
     ],
     "isBlockCoverage": true
    },
    {
     "functionName": "test_apidoc",
     "ranges": [
      {
       "count": 1,
       "endOffset": 2839,
       "startOffset": 2265
      }
     ],
     "isBlockCoverage": true
    },
    {
     "functionName": "",
     "ranges": [
      {
       "count": 1,
       "endOffset": 2835,
       "startOffset": 2352
      }
     ],
     "isBlockCoverage": true
    },
    {
     "functionName": "test_assertXxx",
     "ranges": [
      {
       "count": 1,
       "endOffset": 3379,
       "startOffset": 2884
      }
     ],
     "isBlockCoverage": true
    },
    {
     "functionName": "",
     "ranges": [
      {
       "count": 1,
       "endOffset": 3375,
       "startOffset": 2977
      }
     ],
     "isBlockCoverage": true
    },
    {
     "functionName": "",
     "ranges": [
      {
       "count": 1,
       "endOffset": 3085,
       "startOffset": 3022
      }
     ],
     "isBlockCoverage": true
    },
    {
     "functionName": "",
     "ranges": [
      {
       "count": 1,
       "endOffset": 3212,
       "startOffset": 3149
      }
     ],
     "isBlockCoverage": true
    },
    {
     "functionName": "",
     "ranges": [
      {
       "count": 1,
       "endOffset": 3325,
       "startOffset": 3256
      }
     ],
     "isBlockCoverage": true
    },
    {
     "functionName": "test_childProcessSpawn2",
     "ranges": [
      {
       "count": 1,
       "endOffset": 4793,
       "startOffset": 3433
      }
     ],
     "isBlockCoverage": true
    },
    {
     "functionName": "",
     "ranges": [
      {
       "count": 1,
       "endOffset": 4789,
       "startOffset": 3544
      }
     ],
     "isBlockCoverage": true
    },
    {
     "functionName": "",
     "ranges": [
      {
       "count": 1,
       "endOffset": 4768,
       "startOffset": 3767
      }
     ],
     "isBlockCoverage": true
    },
    {
     "functionName": "test_ciBuildExtXxx",
     "ranges": [
      {
       "count": 1,
       "endOffset": 5475,
       "startOffset": 4842
      }
     ],
     "isBlockCoverage": true
    },
    {
     "functionName": "",
     "ranges": [
      {
       "count": 1,
       "endOffset": 5471,
       "startOffset": 4940
      }
     ],
     "isBlockCoverage": true
    },
    {
     "functionName": "test_dbBind",
     "ranges": [
      {
       "count": 1,
       "endOffset": 14923,
       "startOffset": 5517
      }
     ],
     "isBlockCoverage": true
    },
    {
     "functionName": "test_dbBind",
     "ranges": [
      {
       "count": 1,
       "endOffset": 14919,
       "startOffset": 5605
      }
     ],
     "isBlockCoverage": true
    },
    {
     "functionName": "test_dbBind_exec",
     "ranges": [
      {
       "count": 56,
       "endOffset": 7585,
       "startOffset": 5660
      }
     ],
     "isBlockCoverage": true
    },
    {
     "functionName": "",
     "ranges": [
      {
       "count": 112,
       "endOffset": 7572,
       "startOffset": 6647
      }
     ],
     "isBlockCoverage": true
    },
    {
     "functionName": "test_dbBind_lastBlob",
     "ranges": [
      {
       "count": 56,
       "endOffset": 9937,
       "startOffset": 7594
      },
      {
       "count": 2,
       "endOffset": 8122,
       "startOffset": 7745
      },
      {
       "count": 54,
       "endOffset": 8468,
       "startOffset": 8122
      },
      {
       "count": 10,
       "endOffset": 8544,
       "startOffset": 8468
      },
      {
       "count": 1,
       "endOffset": 8573,
       "startOffset": 8557
      },
      {
       "count": 2,
       "endOffset": 8600,
       "startOffset": 8586
      },
      {
       "count": 3,
       "endOffset": 8685,
       "startOffset": 8613
      },
      {
       "count": 18,
       "endOffset": 9298,
       "startOffset": 8698
      },
      {
       "count": 1,
       "endOffset": 8837,
       "startOffset": 8762
      },
      {
       "count": 3,
       "endOffset": 8936,
       "startOffset": 8854
      },
      {
       "count": 1,
       "endOffset": 9026,
       "startOffset": 8953
      },
      {
       "count": 3,
       "endOffset": 9123,
       "startOffset": 9043
      },
      {
       "count": 10,
       "endOffset": 9257,
       "startOffset": 9140
      },
      {
       "count": 2,
       "endOffset": 9257,
       "startOffset": 9194
      },
      {
       "count": 12,
       "endOffset": 9722,
       "startOffset": 9311
      },
      {
       "count": 1,
       "endOffset": 9444,
       "startOffset": 9362
      },
      {
       "count": 11,
       "endOffset": 9504,
       "startOffset": 9444
      },
      {
       "count": 9,
       "endOffset": 9569,
       "startOffset": 9541
      },
      {
       "count": 7,
       "endOffset": 9699,
       "startOffset": 9588
      },
      {
       "count": 4,
       "endOffset": 9722,
       "startOffset": 9699
      },
      {
       "count": 54,
       "endOffset": 9936,
       "startOffset": 9736
      }
     ],
     "isBlockCoverage": true
    },
    {
     "functionName": "test_dbBind_lastValue",
     "ranges": [
      {
       "count": 56,
       "endOffset": 10805,
       "startOffset": 9946
      },
      {
       "count": 2,
       "endOffset": 10449,
       "startOffset": 10071
      },
      {
       "count": 54,
       "endOffset": 10804,
       "startOffset": 10449
      }
     ],
     "isBlockCoverage": true
    },
    {
     "functionName": "test_dbBind_responseType",
     "ranges": [
      {
       "count": 56,
       "endOffset": 12535,
       "startOffset": 10814
      }
     ],
     "isBlockCoverage": true
    },
    {
     "functionName": "",
     "ranges": [
      {
       "count": 224,
       "endOffset": 12522,
       "startOffset": 11038
      },
      {
       "count": 8,
       "endOffset": 11574,
       "startOffset": 11142
      },
      {
       "count": 216,
       "endOffset": 11839,
       "startOffset": 11574
      },
      {
       "count": 54,
       "endOffset": 12021,
       "startOffset": 11839
      },
      {
       "count": 54,
       "endOffset": 12082,
       "startOffset": 12038
      },
      {
       "count": 54,
       "endOffset": 12190,
       "startOffset": 12099
      },
      {
       "count": 54,
       "endOffset": 12268,
       "startOffset": 12207
      },
      {
       "count": 216,
       "endOffset": 12521,
       "startOffset": 12286
      }
     ],
     "isBlockCoverage": true
    },
    {
     "functionName": "",
     "ranges": [
      {
       "count": 56,
       "endOffset": 14910,
       "startOffset": 14571
      }
     ],
     "isBlockCoverage": true
    },
    {
     "functionName": "test_dbNoopAsync",
     "ranges": [
      {
       "count": 1,
       "endOffset": 18040,
       "startOffset": 14970
      }
     ],
     "isBlockCoverage": true
    },
    {
     "functionName": "",
     "ranges": [
      {
       "count": 1,
       "endOffset": 18036,
       "startOffset": 15067
      }
     ],
     "isBlockCoverage": true
    },
    {
     "functionName": "",
     "ranges": [
      {
       "count": 56,
       "endOffset": 18027,
       "startOffset": 17101
      },
      {
       "count": 23,
       "endOffset": 17434,
       "startOffset": 17230
      },
      {
       "count": 33,
       "endOffset": 17617,
       "startOffset": 17434
      },
      {
       "count": 9,
       "endOffset": 17645,
       "startOffset": 17617
      },
      {
       "count": 24,
       "endOffset": 17697,
       "startOffset": 17662
      },
      {
       "count": 10,
       "endOffset": 17853,
       "startOffset": 17799
      },
      {
       "count": 33,
       "endOffset": 18026,
       "startOffset": 17853
      }
     ],
     "isBlockCoverage": true
    },
    {
     "functionName": "",
     "ranges": [
      {
       "count": 23,
       "endOffset": 17371,
       "startOffset": 17271
      }
     ],
     "isBlockCoverage": true
    },
    {
     "functionName": "test_dbXxxAsync",
     "ranges": [
      {
       "count": 1,
       "endOffset": 25907,
       "startOffset": 18086
      }
     ],
     "isBlockCoverage": true
    },
    {
     "functionName": "test_dbCloseAsync",
     "ranges": [
      {
       "count": 1,
       "endOffset": 18488,
       "startOffset": 18183
      }
     ],
     "isBlockCoverage": true
    },
    {
     "functionName": "",
     "ranges": [
      {
       "count": 1,
       "endOffset": 18395,
       "startOffset": 18335
      }
     ],
     "isBlockCoverage": true
    },
    {
     "functionName": "test_dbExecAndReturnXxx",
     "ranges": [
      {
       "count": 1,
       "endOffset": 20409,
       "startOffset": 18565
      }
     ],
     "isBlockCoverage": true
    },
    {
     "functionName": "test_dbExecAsync",
     "ranges": [
      {
       "count": 1,
       "endOffset": 23306,
       "startOffset": 20479
      }
     ],
     "isBlockCoverage": true
    },
    {
     "functionName": "",
     "ranges": [
      {
       "count": 1,
       "endOffset": 20857,
       "startOffset": 20734
      }
     ],
     "isBlockCoverage": true
    },
    {
     "functionName": "",
     "ranges": [
      {
       "count": 4,
       "endOffset": 23134,
       "startOffset": 20966
      },
      {
       "count": 1,
       "endOffset": 22890,
       "startOffset": 22080
      },
      {
       "count": 3,
       "endOffset": 23124,
       "startOffset": 22890
      }
     ],
     "isBlockCoverage": true
    },
    {
     "functionName": "",
     "ranges": [
      {
       "count": 1,
       "endOffset": 23279,
       "startOffset": 23219
      }
     ],
     "isBlockCoverage": true
    },
    {
     "functionName": "test_dbFileXxx",
     "ranges": [
      {
       "count": 1,
       "endOffset": 24264,
       "startOffset": 23374
      }
     ],
     "isBlockCoverage": true
    },
    {
     "functionName": "",
     "ranges": [
      {
       "count": 1,
       "endOffset": 23730,
       "startOffset": 23606
      }
     ],
     "isBlockCoverage": true
    },
    {
     "functionName": "test_dbOpenAsync",
     "ranges": [
      {
       "count": 1,
       "endOffset": 24646,
       "startOffset": 24334
      }
     ],
     "isBlockCoverage": true
    },
    {
     "functionName": "",
     "ranges": [
      {
       "count": 1,
       "endOffset": 24563,
       "startOffset": 24448
      }
     ],
     "isBlockCoverage": true
    },
    {
     "functionName": "test_dbTableXxx",
     "ranges": [
      {
       "count": 1,
       "endOffset": 25903,
       "startOffset": 24715
      }
     ],
     "isBlockCoverage": true
    },
    {
     "functionName": "test_fsXxx",
     "ranges": [
      {
       "count": 1,
       "endOffset": 26752,
       "startOffset": 25948
      }
     ],
     "isBlockCoverage": true
    },
    {
     "functionName": "",
     "ranges": [
      {
       "count": 1,
       "endOffset": 26748,
       "startOffset": 26033
      }
     ],
     "isBlockCoverage": true
    },
    {
     "functionName": "test_lgbm",
     "ranges": [
      {
       "count": 1,
       "endOffset": 39036,
       "startOffset": 26792
      }
     ],
     "isBlockCoverage": true
    },
    {
     "functionName": "",
     "ranges": [
      {
       "count": 1,
       "endOffset": 39032,
       "startOffset": 26875
      }
     ],
     "isBlockCoverage": true
    },
    {
     "functionName": "testLgbm",
     "ranges": [
      {
       "count": 12,
       "endOffset": 38433,
       "startOffset": 34766
      },
      {
       "count": 6,
       "endOffset": 36861,
       "startOffset": 36598
      },
      {
       "count": 6,
       "endOffset": 37873,
       "startOffset": 37671
      }
     ],
     "isBlockCoverage": true
    },
    {
     "functionName": "",
     "ranges": [
      {
       "count": 36,
       "endOffset": 35421,
       "startOffset": 35146
      }
     ],
     "isBlockCoverage": true
    },
    {
     "functionName": "",
     "ranges": [
      {
       "count": 2,
       "endOffset": 38984,
       "startOffset": 38500
      }
     ],
     "isBlockCoverage": true
    },
    {
     "functionName": "",
     "ranges": [
      {
       "count": 6,
       "endOffset": 38972,
       "startOffset": 38618
      }
     ],
     "isBlockCoverage": true
    },
    {
     "functionName": "",
     "ranges": [
      {
       "count": 12,
       "endOffset": 38956,
       "startOffset": 38739
      }
     ],
     "isBlockCoverage": true
    },
    {
     "functionName": "test_misc",
     "ranges": [
      {
       "count": 1,
       "endOffset": 40261,
       "startOffset": 39076
      }
     ],
     "isBlockCoverage": true
    },
    {
     "functionName": "",
     "ranges": [
      {
       "count": 1,
       "endOffset": 40257,
       "startOffset": 39159
      }
     ],
     "isBlockCoverage": true
    },
    {
     "functionName": "",
     "ranges": [
      {
       "count": 1,
       "endOffset": 39351,
       "startOffset": 39279
      }
     ],
     "isBlockCoverage": true
    },
    {
     "functionName": "",
     "ranges": [
      {
       "count": 1,
       "endOffset": 39524,
       "startOffset": 39466
      }
     ],
     "isBlockCoverage": true
    },
    {
     "functionName": "",
     "ranges": [
      {
       "count": 1,
       "endOffset": 39642,
       "startOffset": 39571
      }
     ],
     "isBlockCoverage": true
    },
    {
     "functionName": "",
     "ranges": [
      {
       "count": 1,
       "endOffset": 39757,
       "startOffset": 39695
      }
     ],
     "isBlockCoverage": true
    },
    {
     "functionName": "",
     "ranges": [
      {
       "count": 1,
       "endOffset": 39929,
       "startOffset": 39855
      }
     ],
     "isBlockCoverage": true
    },
    {
     "functionName": "",
     "ranges": [
      {
       "count": 1,
       "endOffset": 40056,
       "startOffset": 39982
      }
     ],
     "isBlockCoverage": true
    },
    {
     "functionName": "test_sqlite",
     "ranges": [
      {
       "count": 1,
       "endOffset": 146981,
       "startOffset": 40303
      }
     ],
     "isBlockCoverage": true
    },
    {
     "functionName": "test_sqliteError",
     "ranges": [
      {
       "count": 1,
       "endOffset": 42282,
       "startOffset": 40396
      }
     ],
     "isBlockCoverage": true
    },
    {
     "functionName": "",
     "ranges": [
      {
       "count": 30,
       "endOffset": 42273,
       "startOffset": 41992
      }
     ],
     "isBlockCoverage": true
    },
    {
     "functionName": "",
     "ranges": [
      {
       "count": 30,
       "endOffset": 42253,
       "startOffset": 42090
      }
     ],
     "isBlockCoverage": true
    },
    {
     "functionName": "test_sqlite_extension_doublearray_xxx",
     "ranges": [
      {
       "count": 1,
       "endOffset": 44222,
       "startOffset": 42373
      }
     ],
     "isBlockCoverage": true
    },
    {
     "functionName": "",
     "ranges": [
      {
       "count": 23,
       "endOffset": 44213,
       "startOffset": 43282
      },
      {
       "count": 9,
       "endOffset": 43768,
       "startOffset": 43727
      },
      {
       "count": 14,
       "endOffset": 44039,
       "startOffset": 43768
      },
      {
       "count": 9,
       "endOffset": 44212,
       "startOffset": 44039
      }
     ],
     "isBlockCoverage": true
    },
    {
     "functionName": "test_sqlite_extension_idate_xxx",
     "ranges": [
      {
       "count": 1,
       "endOffset": 61231,
       "startOffset": 44307
      }
     ],
     "isBlockCoverage": true
    },
    {
     "functionName": "idateArgNormalize",
     "ranges": [
      {
       "count": 588,
       "endOffset": 46147,
       "startOffset": 44436
      },
      {
       "count": 556,
       "endOffset": 44753,
       "startOffset": 44746
      },
      {
       "count": 252,
       "endOffset": 45932,
       "startOffset": 44769
      },
      {
       "count": 38,
       "endOffset": 44929,
       "startOffset": 44857
      },
      {
       "count": 214,
       "endOffset": 44974,
       "startOffset": 44929
      },
      {
       "count": 20,
       "endOffset": 45095,
       "startOffset": 44974
      },
      {
       "count": 194,
       "endOffset": 45141,
       "startOffset": 45095
      },
      {
       "count": 20,
       "endOffset": 45259,
       "startOffset": 45141
      },
      {
       "count": 174,
       "endOffset": 45306,
       "startOffset": 45259
      },
      {
       "count": 20,
       "endOffset": 45421,
       "startOffset": 45306
      },
      {
       "count": 154,
       "endOffset": 45469,
       "startOffset": 45421
      },
      {
       "count": 10,
       "endOffset": 45538,
       "startOffset": 45469
      },
      {
       "count": 144,
       "endOffset": 45587,
       "startOffset": 45538
      },
      {
       "count": 10,
       "endOffset": 45653,
       "startOffset": 45587
      },
      {
       "count": 134,
       "endOffset": 45758,
       "startOffset": 45653
      },
      {
       "count": 88,
       "endOffset": 45818,
       "startOffset": 45758
      },
      {
       "count": 20,
       "endOffset": 45817,
       "startOffset": 45786
      },
      {
       "count": 66,
       "endOffset": 45909,
       "startOffset": 45837
      },
      {
       "count": 68,
       "endOffset": 45932,
       "startOffset": 45909
      },
      {
       "count": 304,
       "endOffset": 46099,
       "startOffset": 45945
      },
      {
       "count": 142,
       "endOffset": 46076,
       "startOffset": 46004
      },
      {
       "count": 162,
       "endOffset": 46099,
       "startOffset": 46076
      },
      {
       "count": 262,
       "endOffset": 46146,
       "startOffset": 46113
      }
     ],
     "isBlockCoverage": true
    },
    {
     "functionName": "idateArgYmdTruncate",
     "ranges": [
      {
       "count": 268,
       "endOffset": 44712,
       "startOffset": 44497
      },
      {
       "count": 238,
       "endOffset": 44656,
       "startOffset": 44580
      },
      {
       "count": 30,
       "endOffset": 44711,
       "startOffset": 44656
      }
     ],
     "isBlockCoverage": true
    },
    {
     "functionName": "",
     "ranges": [
      {
       "count": 15,
       "endOffset": 48449,
       "startOffset": 46747
      }
     ],
     "isBlockCoverage": true
    },
    {
     "functionName": "",
     "ranges": [
      {
       "count": 570,
       "endOffset": 48437,
       "startOffset": 48320
      }
     ],
     "isBlockCoverage": true
    },
    {
     "functionName": "",
     "ranges": [
      {
       "count": 2,
       "endOffset": 48821,
       "startOffset": 48553
      }
     ],
     "isBlockCoverage": true
    },
    {
     "functionName": "",
     "ranges": [
      {
       "count": 4,
       "endOffset": 48809,
       "startOffset": 48692
      }
     ],
     "isBlockCoverage": true
    },
    {
     "functionName": "",
     "ranges": [
      {
       "count": 13,
       "endOffset": 49631,
       "startOffset": 49279
      }
     ],
     "isBlockCoverage": true
    },
    {
     "functionName": "",
     "ranges": [
      {
       "count": 52,
       "endOffset": 49619,
       "startOffset": 49502
      }
     ],
     "isBlockCoverage": true
    },
    {
     "functionName": "",
     "ranges": [
      {
       "count": 2,
       "endOffset": 50686,
       "startOffset": 49738
      }
     ],
     "isBlockCoverage": true
    },
    {
     "functionName": "",
     "ranges": [
      {
       "count": 20,
       "endOffset": 50667,
       "startOffset": 50301
      }
     ],
     "isBlockCoverage": true
    },
    {
     "functionName": "",
     "ranges": [
      {
       "count": 40,
       "endOffset": 50651,
       "startOffset": 50388
      }
     ],
     "isBlockCoverage": true
    },
    {
     "functionName": "",
     "ranges": [
      {
       "count": 2,
       "endOffset": 51696,
       "startOffset": 50800
      }
     ],
     "isBlockCoverage": true
    },
    {
     "functionName": "",
     "ranges": [
      {
       "count": 16,
       "endOffset": 51684,
       "startOffset": 51305
      },
      {
       "count": 8,
       "endOffset": 51528,
       "startOffset": 51509
      },
      {
       "count": 4,
       "endOffset": 51528,
       "startOffset": 51520
      },
      {
       "count": 8,
       "endOffset": 51560,
       "startOffset": 51553
      }
     ],
     "isBlockCoverage": true
    },
    {
     "functionName": "",
     "ranges": [
      {
       "count": 2,
       "endOffset": 52352,
       "startOffset": 51810
      }
     ],
     "isBlockCoverage": true
    },
    {
     "functionName": "",
     "ranges": [
      {
       "count": 8,
       "endOffset": 52340,
       "startOffset": 52087
      }
     ],
     "isBlockCoverage": true
    },
    {
     "functionName": "",
     "ranges": [
      {
       "count": 2,
       "endOffset": 53358,
       "startOffset": 52470
      }
     ],
     "isBlockCoverage": true
    },
    {
     "functionName": "",
     "ranges": [
      {
       "count": 16,
       "endOffset": 53346,
       "startOffset": 52967
      },
      {
       "count": 8,
       "endOffset": 53190,
       "startOffset": 53171
      },
      {
       "count": 4,
       "endOffset": 53190,
       "startOffset": 53182
      },
      {
       "count": 8,
       "endOffset": 53222,
       "startOffset": 53215
      }
     ],
     "isBlockCoverage": true
    },
    {
     "functionName": "",
     "ranges": [
      {
       "count": 2,
       "endOffset": 54006,
       "startOffset": 53476
      }
     ],
     "isBlockCoverage": true
    },
    {
     "functionName": "",
     "ranges": [
      {
       "count": 8,
       "endOffset": 53994,
       "startOffset": 53741
      }
     ],
     "isBlockCoverage": true
    },
    {
     "functionName": "",
     "ranges": [
      {
       "count": 2,
       "endOffset": 55020,
       "startOffset": 54120
      }
     ],
     "isBlockCoverage": true
    },
    {
     "functionName": "",
     "ranges": [
      {
       "count": 16,
       "endOffset": 55001,
       "startOffset": 54635
      }
     ],
     "isBlockCoverage": true
    },
    {
     "functionName": "",
     "ranges": [
      {
       "count": 32,
       "endOffset": 54985,
       "startOffset": 54722
      }
     ],
     "isBlockCoverage": true
    },
    {
     "functionName": "",
     "ranges": [
      {
       "count": 2,
       "endOffset": 56399,
       "startOffset": 55132
      }
     ],
     "isBlockCoverage": true
    },
    {
     "functionName": "",
     "ranges": [
      {
       "count": 24,
       "endOffset": 56380,
       "startOffset": 55858
      }
     ],
     "isBlockCoverage": true
    },
    {
     "functionName": "",
     "ranges": [
      {
       "count": 48,
       "endOffset": 56364,
       "startOffset": 55959
      },
      {
       "count": 24,
       "endOffset": 56257,
       "startOffset": 56230
      },
      {
       "count": 14,
       "endOffset": 56257,
       "startOffset": 56245
      },
      {
       "count": 24,
       "endOffset": 56297,
       "startOffset": 56286
      }
     ],
     "isBlockCoverage": true
    },
    {
     "functionName": "",
     "ranges": [
      {
       "count": 1,
       "endOffset": 57628,
       "startOffset": 56484
      }
     ],
     "isBlockCoverage": true
    },
    {
     "functionName": "",
     "ranges": [
      {
       "count": 10,
       "endOffset": 57609,
       "startOffset": 57087
      }
     ],
     "isBlockCoverage": true
    },
    {
     "functionName": "",
     "ranges": [
      {
       "count": 20,
       "endOffset": 57593,
       "startOffset": 57188
      },
      {
       "count": 10,
       "endOffset": 57486,
       "startOffset": 57459
      },
      {
       "count": 5,
       "endOffset": 57486,
       "startOffset": 57474
      },
      {
       "count": 10,
       "endOffset": 57526,
       "startOffset": 57515
      }
     ],
     "isBlockCoverage": true
    },
    {
     "functionName": "",
     "ranges": [
      {
       "count": 2,
       "endOffset": 58641,
       "startOffset": 57746
      }
     ],
     "isBlockCoverage": true
    },
    {
     "functionName": "",
     "ranges": [
      {
       "count": 20,
       "endOffset": 58629,
       "startOffset": 58379
      }
     ],
     "isBlockCoverage": true
    },
    {
     "functionName": "",
     "ranges": [
      {
       "count": 6,
       "endOffset": 59960,
       "startOffset": 58881
      }
     ],
     "isBlockCoverage": true
    },
    {
     "functionName": "",
     "ranges": [
      {
       "count": 72,
       "endOffset": 59941,
       "startOffset": 59531
      }
     ],
     "isBlockCoverage": true
    },
    {
     "functionName": "",
     "ranges": [
      {
       "count": 144,
       "endOffset": 59925,
       "startOffset": 59628
      }
     ],
     "isBlockCoverage": true
    },
    {
     "functionName": "",
     "ranges": [
      {
       "count": 978,
       "endOffset": 61222,
       "startOffset": 60020
      },
      {
       "count": 848,
       "endOffset": 60349,
       "startOffset": 60305
      },
      {
       "count": 130,
       "endOffset": 60699,
       "startOffset": 60366
      },
      {
       "count": 114,
       "endOffset": 60636,
       "startOffset": 60413
      },
      {
       "count": 18,
       "endOffset": 60544,
       "startOffset": 60494
      },
      {
       "count": 96,
       "endOffset": 60618,
       "startOffset": 60565
      },
      {
       "count": 16,
       "endOffset": 60699,
       "startOffset": 60653
      }
     ],
     "isBlockCoverage": true
    },
    {
     "functionName": "test_sqlite_extension_math",
     "ranges": [
      {
       "count": 1,
       "endOffset": 71749,
       "startOffset": 61311
      }
     ],
     "isBlockCoverage": true
    },
    {
     "functionName": "",
     "ranges": [
      {
       "count": 30,
       "endOffset": 71741,
       "startOffset": 71001
      }
     ],
     "isBlockCoverage": true
    },
    {
     "functionName": "",
     "ranges": [
      {
       "count": 148,
       "endOffset": 71729,
       "startOffset": 71097
      },
      {
       "count": 24,
       "endOffset": 71333,
       "startOffset": 71302
      },
      {
       "count": 124,
       "endOffset": 71380,
       "startOffset": 71354
      }
     ],
     "isBlockCoverage": true
    },
    {
     "functionName": "test_sqlite_extension_quantile",
     "ranges": [
      {
       "count": 1,
       "endOffset": 76726,
       "startOffset": 71833
      }
     ],
     "isBlockCoverage": true
    },
    {
     "functionName": "",
     "ranges": [
      {
       "count": 1,
       "endOffset": 72470,
       "startOffset": 71938
      }
     ],
     "isBlockCoverage": true
    },
    {
     "functionName": "",
     "ranges": [
      {
       "count": 30,
       "endOffset": 74305,
       "startOffset": 73920
      }
     ],
     "isBlockCoverage": true
    },
    {
     "functionName": "",
     "ranges": [
      {
       "count": 38,
       "endOffset": 76717,
       "startOffset": 74328
      },
      {
       "count": 19,
       "endOffset": 74885,
       "startOffset": 74780
      },
      {
       "count": 19,
       "endOffset": 74935,
       "startOffset": 74902
      },
      {
       "count": 6,
       "endOffset": 75273,
       "startOffset": 75267
      },
      {
       "count": 32,
       "endOffset": 75456,
       "startOffset": 75353
      }
     ],
     "isBlockCoverage": true
    },
    {
     "functionName": "",
     "ranges": [
      {
       "count": 422,
       "endOffset": 74600,
       "startOffset": 74532
      }
     ],
     "isBlockCoverage": true
    },
    {
     "functionName": "",
     "ranges": [
      {
       "count": 422,
       "endOffset": 74686,
       "startOffset": 74609
      }
     ],
     "isBlockCoverage": true
    },
    {
     "functionName": "",
     "ranges": [
      {
       "count": 267,
       "endOffset": 75037,
       "startOffset": 74977
      }
     ],
     "isBlockCoverage": true
    },
    {
     "functionName": "",
     "ranges": [
      {
       "count": 267,
       "endOffset": 75185,
       "startOffset": 75103
      }
     ],
     "isBlockCoverage": true
    },
    {
     "functionName": "",
     "ranges": [
      {
       "count": 76,
       "endOffset": 76704,
       "startOffset": 75587
      },
      {
       "count": 12,
       "endOffset": 76358,
       "startOffset": 76351
      }
     ],
     "isBlockCoverage": true
    },
    {
     "functionName": "test_sqlite_extension_win_avgx",
     "ranges": [
      {
       "count": 1,
       "endOffset": 82400,
       "startOffset": 76810
      }
     ],
     "isBlockCoverage": true
    },
    {
     "functionName": "test_win_avgx_aggregate",
     "ranges": [
      {
       "count": 4,
       "endOffset": 79334,
       "startOffset": 76927
      },
      {
       "count": 3,
       "endOffset": 77293,
       "startOffset": 77153
      }
     ],
     "isBlockCoverage": true
    },
    {
     "functionName": "",
     "ranges": [
      {
       "count": 48,
       "endOffset": 77848,
       "startOffset": 77769
      }
     ],
     "isBlockCoverage": true
    },
    {
     "functionName": "",
     "ranges": [
      {
       "count": 48,
       "endOffset": 79271,
       "startOffset": 78762
      }
     ],
     "isBlockCoverage": true
    },
    {
     "functionName": "",
     "ranges": [
      {
       "count": 480,
       "endOffset": 79224,
       "startOffset": 78833
      },
      {
       "count": 240,
       "endOffset": 78944,
       "startOffset": 78940
      },
      {
       "count": 80,
       "endOffset": 78976,
       "startOffset": 78965
      },
      {
       "count": 8,
       "endOffset": 79071,
       "startOffset": 78978
      },
      {
       "count": 472,
       "endOffset": 79173,
       "startOffset": 79071
      }
     ],
     "isBlockCoverage": true
    },
    {
     "functionName": "",
     "ranges": [
      {
       "count": 1,
       "endOffset": 81074,
       "startOffset": 79672
      }
     ],
     "isBlockCoverage": true
    },
    {
     "functionName": "",
     "ranges": [
      {
       "count": 1,
       "endOffset": 80043,
       "startOffset": 79825
      }
     ],
     "isBlockCoverage": true
    },
    {
     "functionName": "",
     "ranges": [
      {
       "count": 1,
       "endOffset": 80500,
       "startOffset": 80432
      }
     ],
     "isBlockCoverage": true
    },
    {
     "functionName": "",
     "ranges": [
      {
       "count": 1,
       "endOffset": 81006,
       "startOffset": 80938
      }
     ],
     "isBlockCoverage": true
    },
    {
     "functionName": "test_sqlite_extension_win_emax",
     "ranges": [
      {
       "count": 1,
       "endOffset": 88609,
       "startOffset": 82484
      }
     ],
     "isBlockCoverage": true
    },
    {
     "functionName": "test_win_emax_aggregate",
     "ranges": [
      {
       "count": 4,
       "endOffset": 85168,
       "startOffset": 82601
      },
      {
       "count": 3,
       "endOffset": 83010,
       "startOffset": 82870
      }
     ],
     "isBlockCoverage": true
    },
    {
     "functionName": "",
     "ranges": [
      {
       "count": 48,
       "endOffset": 83670,
       "startOffset": 83591
      }
     ],
     "isBlockCoverage": true
    },
    {
     "functionName": "",
     "ranges": [
      {
       "count": 48,
       "endOffset": 85105,
       "startOffset": 84596
      }
     ],
     "isBlockCoverage": true
    },
    {
     "functionName": "",
     "ranges": [
      {
       "count": 480,
       "endOffset": 85058,
       "startOffset": 84667
      },
      {
       "count": 240,
       "endOffset": 84778,
       "startOffset": 84774
      },
      {
       "count": 80,
       "endOffset": 84810,
       "startOffset": 84799
      },
      {
       "count": 8,
       "endOffset": 84905,
       "startOffset": 84812
      },
      {
       "count": 472,
       "endOffset": 85007,
       "startOffset": 84905
      }
     ],
     "isBlockCoverage": true
    },
    {
     "functionName": "",
     "ranges": [
      {
       "count": 1,
       "endOffset": 87193,
       "startOffset": 85506
      }
     ],
     "isBlockCoverage": true
    },
    {
     "functionName": "",
     "ranges": [
      {
       "count": 1,
       "endOffset": 85878,
       "startOffset": 85659
      }
     ],
     "isBlockCoverage": true
    },
    {
     "functionName": "",
     "ranges": [
      {
       "count": 1,
       "endOffset": 86180,
       "startOffset": 85955
      }
     ],
     "isBlockCoverage": true
    },
    {
     "functionName": "",
     "ranges": [
      {
       "count": 1,
       "endOffset": 86629,
       "startOffset": 86561
      }
     ],
     "isBlockCoverage": true
    },
    {
     "functionName": "",
     "ranges": [
      {
       "count": 1,
       "endOffset": 87125,
       "startOffset": 87057
      }
     ],
     "isBlockCoverage": true
    },
    {
     "functionName": "test_sqlite_extension_win_quantilex",
     "ranges": [
      {
       "count": 1,
       "endOffset": 98681,
       "startOffset": 88698
      }
     ],
     "isBlockCoverage": true
    },
    {
     "functionName": "test_win_quantilex_aggregate",
     "ranges": [
      {
       "count": 14,
       "endOffset": 91512,
       "startOffset": 88820
      },
      {
       "count": 7,
       "endOffset": 89213,
       "startOffset": 89073
      }
     ],
     "isBlockCoverage": true
    },
    {
     "functionName": "",
     "ranges": [
      {
       "count": 168,
       "endOffset": 89886,
       "startOffset": 89807
      }
     ],
     "isBlockCoverage": true
    },
    {
     "functionName": "",
     "ranges": [
      {
       "count": 168,
       "endOffset": 91449,
       "startOffset": 90940
      }
     ],
     "isBlockCoverage": true
    },
    {
     "functionName": "",
     "ranges": [
      {
       "count": 1680,
       "endOffset": 91402,
       "startOffset": 91011
      },
      {
       "count": 140,
       "endOffset": 91154,
       "startOffset": 91143
      },
      {
       "count": 14,
       "endOffset": 91249,
       "startOffset": 91156
      },
      {
       "count": 1666,
       "endOffset": 91351,
       "startOffset": 91249
      }
     ],
     "isBlockCoverage": true
    },
    {
     "functionName": "",
     "ranges": [
      {
       "count": 1,
       "endOffset": 93583,
       "startOffset": 91846
      }
     ],
     "isBlockCoverage": true
    },
    {
     "functionName": "",
     "ranges": [
      {
       "count": 1,
       "endOffset": 92228,
       "startOffset": 92004
      }
     ],
     "isBlockCoverage": true
    },
    {
     "functionName": "",
     "ranges": [
      {
       "count": 1,
       "endOffset": 92535,
       "startOffset": 92305
      }
     ],
     "isBlockCoverage": true
    },
    {
     "functionName": "",
     "ranges": [
      {
       "count": 1,
       "endOffset": 92999,
       "startOffset": 92931
      }
     ],
     "isBlockCoverage": true
    },
    {
     "functionName": "",
     "ranges": [
      {
       "count": 1,
       "endOffset": 93515,
       "startOffset": 93447
      }
     ],
     "isBlockCoverage": true
    },
    {
     "functionName": "test_sqlite_extension_win_sinefit2",
     "ranges": [
      {
       "count": 1,
       "endOffset": 141394,
       "startOffset": 98769
      }
     ],
     "isBlockCoverage": true
    },
    {
     "functionName": "sqlSinefitExtractLnr",
     "ranges": [
      {
       "count": 6,
       "endOffset": 100348,
       "startOffset": 98957
      }
     ],
     "isBlockCoverage": true
    },
    {
     "functionName": "test_win_sinefit2_aggregate",
     "ranges": [
      {
       "count": 1,
       "endOffset": 106938,
       "startOffset": 100357
      }
     ],
     "isBlockCoverage": true
    },
    {
     "functionName": "",
     "ranges": [
      {
       "count": 10,
       "endOffset": 106875,
       "startOffset": 103126
      },
      {
       "count": 1,
       "endOffset": 106492,
       "startOffset": 106332
      },
      {
       "count": 1,
       "endOffset": 106669,
       "startOffset": 106509
      },
      {
       "count": 8,
       "endOffset": 106814,
       "startOffset": 106686
      }
     ],
     "isBlockCoverage": true
    },
    {
     "functionName": "",
     "ranges": [
      {
       "count": 1,
       "endOffset": 113808,
       "startOffset": 112860
      }
     ],
     "isBlockCoverage": true
    },
    {
     "functionName": "",
     "ranges": [
      {
       "count": 1,
       "endOffset": 113246,
       "startOffset": 113017
      }
     ],
     "isBlockCoverage": true
    },
    {
     "functionName": "",
     "ranges": [
      {
       "count": 1,
       "endOffset": 113740,
       "startOffset": 113672
      }
     ],
     "isBlockCoverage": true
    },
    {
     "functionName": "",
     "ranges": [
      {
       "count": 1,
       "endOffset": 115339,
       "startOffset": 113894
      }
     ],
     "isBlockCoverage": true
    },
    {
     "functionName": "",
     "ranges": [
      {
       "count": 1,
       "endOffset": 116793,
       "startOffset": 115425
      }
     ],
     "isBlockCoverage": true
    },
    {
     "functionName": "",
     "ranges": [
      {
       "count": 1,
       "endOffset": 141373,
       "startOffset": 118395
      }
     ],
     "isBlockCoverage": true
    },
    {
     "functionName": "",
     "ranges": [
      {
       "count": 1012,
       "endOffset": 138294,
       "startOffset": 138040
      }
     ],
     "isBlockCoverage": true
    },
    {
     "functionName": "",
     "ranges": [
      {
       "count": 1012,
       "endOffset": 140666,
       "startOffset": 139990
      }
     ],
     "isBlockCoverage": true
    },
    {
     "functionName": "",
     "ranges": [
      {
       "count": 7084,
       "endOffset": 140632,
       "startOffset": 140379
      },
      {
       "count": 6072,
       "endOffset": 140537,
       "startOffset": 140521
      },
      {
       "count": 1012,
       "endOffset": 140575,
       "startOffset": 140570
      }
     ],
     "isBlockCoverage": true
    },
    {
     "functionName": "test_sqlite_extension_win_sumx",
     "ranges": [
      {
       "count": 1,
       "endOffset": 146977,
       "startOffset": 141478
      }
     ],
     "isBlockCoverage": true
    },
    {
     "functionName": "test_win_sumx_aggregate",
     "ranges": [
      {
       "count": 4,
       "endOffset": 144002,
       "startOffset": 141595
      },
      {
       "count": 3,
       "endOffset": 141961,
       "startOffset": 141821
      }
     ],
     "isBlockCoverage": true
    },
    {
     "functionName": "",
     "ranges": [
      {
       "count": 48,
       "endOffset": 142516,
       "startOffset": 142437
      }
     ],
     "isBlockCoverage": true
    },
    {
     "functionName": "",
     "ranges": [
      {
       "count": 48,
       "endOffset": 143939,
       "startOffset": 143430
      }
     ],
     "isBlockCoverage": true
    },
    {
     "functionName": "",
     "ranges": [
      {
       "count": 480,
       "endOffset": 143892,
       "startOffset": 143501
      },
      {
       "count": 240,
       "endOffset": 143612,
       "startOffset": 143608
      },
      {
       "count": 80,
       "endOffset": 143644,
       "startOffset": 143633
      },
      {
       "count": 8,
       "endOffset": 143739,
       "startOffset": 143646
      },
      {
       "count": 472,
       "endOffset": 143841,
       "startOffset": 143739
      }
     ],
     "isBlockCoverage": true
    },
    {
     "functionName": "",
     "ranges": [
      {
       "count": 1,
       "endOffset": 145742,
       "startOffset": 144340
      }
     ],
     "isBlockCoverage": true
    },
    {
     "functionName": "",
     "ranges": [
      {
       "count": 1,
       "endOffset": 144711,
       "startOffset": 144493
      }
     ],
     "isBlockCoverage": true
    },
    {
     "functionName": "",
     "ranges": [
      {
       "count": 1,
       "endOffset": 145168,
       "startOffset": 145100
      }
     ],
     "isBlockCoverage": true
    },
    {
     "functionName": "",
     "ranges": [
      {
       "count": 1,
       "endOffset": 145674,
       "startOffset": 145606
      }
     ],
     "isBlockCoverage": true
    },
    {
     "functionName": "test_sqlmathWebworkerInit",
     "ranges": [
      {
       "count": 1,
       "endOffset": 147354,
       "startOffset": 147037
      }
     ],
     "isBlockCoverage": true
    },
    {
     "functionName": "",
     "ranges": [
      {
       "count": 1,
       "endOffset": 147350,
       "startOffset": 147152
      }
     ],
     "isBlockCoverage": true
    }
   ]
  }
 ]
}